exceptional_auth/README.md
exceptional_auth/RELEASE_NOTES.md
exceptional_auth/VERSION
exceptional_auth/__init__.py
exceptional_auth/py.typed
exceptional_auth/__pycache__/__init__.cpython-36.pyc
exceptional_auth-0.6.1.dist-info/LICENSE
exceptional_auth-0.6.1.dist-info/METADATA
exceptional_auth-0.6.1.dist-info/WHEEL
exceptional_auth-0.6.1.dist-info/top_level.txt
exceptional_auth-0.6.1.dist-info/RECORD
