Metadata-Version: 2.1
Name: exceptional-auth
Version: 0.6.1
Summary: Exception-based authentication helpers for django
Home-page: https://github.com/quadrant-newmedia/exceptional_auth
Author: Alex Fischer
Author-email: alex@quadrant.net
License: UNKNOWN
Platform: UNKNOWN
Classifier: Programming Language :: Python :: 3
Classifier: License :: OSI Approved :: MIT License
Classifier: Operating System :: OS Independent
Requires-Python: >=3.7
Requires-Dist: Django (<6,>=3)
Requires-Dist: django-types (<1,>=0.19.1)
